{
	"activityModels":[
		{
			"description":"",
			"exported":false,
			"module":"",
			"name":"",
			"params":[],
			"path":"",
			"type":"com.grouter.demo.MainActivity"
		},
		{
			"description":"",
			"exported":true,
			"module":"",
			"name":"",
			"params":[],
			"path":"",
			"type":"com.grouter.demo.activity.LoginActivity"
		},
		{
			"description":"",
			"exported":true,
			"module":"",
			"name":"",
			"params":[],
			"path":"",
			"type":"com.grouter.demo.activity.OverridePendingTransitionActivity"
		},
		{
			"description":"",
			"exported":true,
			"module":"",
			"name":"",
			"params":[],
			"path":"",
			"type":"com.grouter.demo.activity.OverridePendingTransitionTargetActivity"
		},
		{
			"description":"",
			"exported":true,
			"module":"",
			"name":"",
			"params":[
				{
					"name":"cinemaId",
					"queryName":"",
					"rawType":"java.lang.String",
					"type":"java.lang.String"
				}
			],
			"path":"cinema",
			"type":"com.grouter.demo.activity.CinemaActivity"
		},
		{
			"description":"",
			"exported":true,
			"module":"",
			"name":"",
			"params":[
				{
					"name":"cinemaId",
					"queryName":"",
					"rawType":"java.lang.String",
					"type":"java.lang.String"
				}
			],
			"path":"cinema/detail",
			"type":"com.grouter.demo.activity.CinemaDetailActivity"
		},
		{
			"description":"",
			"exported":true,
			"module":"",
			"name":"",
			"params":[
				{
					"name":"mid",
					"queryName":"",
					"rawType":"java.lang.String",
					"type":"java.lang.String"
				}
			],
			"path":"moment",
			"type":"com.grouter.demo.activity.MomentActivity"
		},
		{
			"description":"",
			"exported":true,
			"module":"",
			"name":"",
			"params":[
				{
					"name":"mid",
					"queryName":"",
					"rawType":"java.lang.String",
					"type":"java.lang.String"
				}
			],
			"path":"moment/list",
			"type":"com.grouter.demo.activity.MomentListActivity"
		},
		{
			"description":"",
			"exported":true,
			"module":"",
			"name":"",
			"params":[
				{
					"name":"movieId",
					"queryName":"",
					"rawType":"java.lang.String",
					"type":"java.lang.String"
				}
			],
			"path":"movie",
			"type":"com.grouter.demo.activity.MovieActivity"
		},
		{
			"description":"",
			"exported":true,
			"module":"",
			"name":"",
			"params":[
				{
					"name":"movieId",
					"queryName":"",
					"rawType":"java.lang.String",
					"type":"java.lang.String"
				}
			],
			"path":"movie/photo",
			"type":"com.grouter.demo.activity.MoviePhotoActivity"
		},
		{
			"description":"",
			"exported":true,
			"module":"",
			"name":"",
			"params":[
				{
					"name":"movieId",
					"queryName":"",
					"rawType":"java.lang.String",
					"type":"java.lang.String"
				}
			],
			"path":"movie/worker",
			"type":"com.grouter.demo.activity.MovieWorkerActivity"
		},
		{
			"description":"",
			"exported":false,
			"module":"",
			"name":"",
			"params":[],
			"path":"settings",
			"type":"com.grouter.demo.activity.SettingsActivity"
		},
		{
			"description":"",
			"exported":false,
			"module":"",
			"name":"",
			"params":[],
			"path":"settings/about_us,about_us",
			"type":"com.grouter.demo.activity.AboutUsActivity"
		},
		{
			"description":"",
			"exported":true,
			"module":"",
			"name":"",
			"params":[],
			"path":"settings/network/ping",
			"type":"com.grouter.demo.activity.NetworkPingActivity"
		},
		{
			"description":"展示用户信息",
			"exported":true,
			"module":"",
			"name":"用户信息页",
			"params":[
				{
					"name":"uid",
					"queryName":"",
					"rawType":"java.lang.Integer",
					"type":"java.lang.Integer"
				},
				{
					"name":"name",
					"queryName":"",
					"rawType":"java.lang.String",
					"type":"java.lang.String"
				},
				{
					"name":"user",
					"queryName":"",
					"rawType":"com.grouter.demo.base.model.User",
					"type":"Object"
				},
				{
					"name":"users",
					"queryName":"",
					"rawType":"java.util.List<com.grouter.demo.base.model.User>",
					"type":"java.util.List"
				},
				{
					"name":"uidArray",
					"queryName":"",
					"rawType":"int[]",
					"type":"int[]"
				}
			],
			"path":"user",
			"type":"com.grouter.demo.activity.UserActivity"
		}
	],
	"componentModels":[
		{
			"constructors":[
				{
					"parameterNames":[],
					"parameterTypes":[]
				},
				{
					"parameterNames":[
						"context",
						"uid",
						"sums"
					],
					"parameterTypes":[
						"android.content.Context",
						"int",
						"int[]"
					]
				},
				{
					"parameterNames":[
						"activity"
					],
					"parameterTypes":[
						"android.app.Activity"
					]
				}
			],
			"description":"本地缓存和网络请求",
			"implement":"com.grouter.demo.service.FeedServiceImpl",
			"name":"动态服务",
			"path":"",
			"protocol":"com.grouter.demo.base.service.FeedService"
		}
	],
	"delegateModels":[
		{
			"constructor":[
				{
					"parameterNames":[],
					"parameterTypes":[]
				}
			],
			"methods":[
				{
					"name":"getUser",
					"parameterNames":[
						"uid"
					],
					"parameterTypes":[
						"int"
					],
					"returns":"com.grouter.demo.base.model.User"
				},
				{
					"name":"getUser",
					"parameterNames":[
						"name"
					],
					"parameterTypes":[
						"java.lang.String"
					],
					"returns":"com.grouter.demo.base.model.User"
				},
				{
					"name":"listUser",
					"parameterNames":[
						"uids"
					],
					"parameterTypes":[
						"int[]"
					],
					"returns":"java.util.List<com.grouter.demo.base.model.User>"
				},
				{
					"name":"delete",
					"parameterNames":[
						"user",
						"stringBuilder"
					],
					"parameterTypes":[
						"com.grouter.demo.base.model.User",
						"java.lang.StringBuilder"
					],
					"returns":"void"
				}
			],
			"type":"com.grouter.demo.delegate.UserViewModel"
		},
		{
			"constructor":[
				{
					"parameterNames":[
						"context"
					],
					"parameterTypes":[
						"android.content.Context"
					]
				}
			],
			"methods":[
				{
					"name":"getMoment",
					"parameterNames":[
						"uid"
					],
					"parameterTypes":[
						"int"
					],
					"returns":"com.grouter.demo.base.model.Moment"
				},
				{
					"name":"listMoment",
					"parameterNames":[
						"ids"
					],
					"parameterTypes":[
						"int[]"
					],
					"returns":"java.util.List<com.grouter.demo.base.model.Moment>"
				},
				{
					"name":"listMoment2",
					"parameterNames":[
						"ids"
					],
					"parameterTypes":[
						"int[]"
					],
					"returns":"java.util.Vector<com.grouter.demo.base.model.Moment>"
				},
				{
					"name":"delete",
					"parameterNames":[
						"moment"
					],
					"parameterTypes":[
						"com.grouter.demo.base.model.Moment"
					],
					"returns":"void"
				}
			],
			"type":"com.grouter.demo.delegate.MomentViewModel"
		}
	],
	"interceptorModels":[
		{
			"priority":0,
			"type":"com.grouter.demo.AppRouterInterceptor"
		},
		{
			"priority":0,
			"type":"com.grouter.demo.LoginRouterInterceptor"
		}
	],
	"taskModels":[
		{
			"description":"",
			"name":"",
			"params":[
				{
					"name":"name",
					"queryName":"",
					"rawType":"java.lang.String",
					"type":"java.lang.String"
				},
				{
					"name":"context",
					"queryName":"",
					"rawType":"android.content.Context",
					"type":"android.content.Context"
				},
				{
					"name":"activity",
					"queryName":"",
					"rawType":"android.app.Activity",
					"type":"android.app.Activity"
				},
				{
					"name":"application",
					"queryName":"",
					"rawType":"android.app.Application",
					"type":"android.app.Application"
				}
			],
			"path":"UserList",
			"returns":"List<User>",
			"type":"com.grouter.demo.service.UserListTask"
		}
	]
}